{
  "content": [
    {
      "type": "text",
      "text": "# Andrewartha\n\nAndrewartha and Trewartha are Cornish family names.\nEtymology\nCornish Names says:\n*Nouns:\n**\"tre\" a \"town\", feminine, maybe a hamlet or house\n**\"tref: village, town\", Brythonic Celt Welsh about 4-500 AD\n*Adjectives:\n**\"Wartha\": \"upper\" (maybe higher or greater or on a hill)\n***cf. \"Wollas\": \"lower\" (maybe smaller or lesser or in a valley, of the two).\n*Definite article:\n**\"An\" used as: \"of the\", \"in the\", \"on the\", \"at the\", in place names. Brythonic Celt Cornish language (Dexter, p.&nbsp;18).\nThe book mentions \"Trewartha\" (p.&nbsp;25), and \"Andrewartha\" (p.&nbsp;60).\nThe Handbook of Cornish Names states: \"Trewartha\" is a Cornish name meaning \"Upper Farm\" or \"Upper Homestead\".\nPeople\n*Herbert Andrewartha (1907–1992), Australian research scientist in the fields of entomology, biology, zoology and animal ecology\n*Janet Andrewartha (1951–2024), Australian actress\n*John Andrewartha, Cornish-born American architect and civil engineer\n*Roy Andrewartha, Welsh snooker player, finalist at the 1977, 1978, 1979 & 1984 World Snooker Championships\n*Jake Andrewartha, Australian Olympian judoka, 2014 Commonwealth Games Medalist and professional wrestler\nReferences"
    }
  ]
}