{
  "content": [
    {
      "type": "text",
      "text": "{\n  \"articles\": [\n    \"YAMAZAKI BAKING Co., Ltd\",\n    \"Battle of Van Nest's Mills\",\n    \"Looking For a Boy\",\n    \"Vice President of the House of Representatives of Puerto Rico\",\n    \"W. Ward Reynoldson\",\n    \"Dragons of the Dwarven Depths\",\n    \"Edward James Young\",\n    \"Battle of Cēsis (1210)\",\n    \"The Walking Drum (book)\",\n    \"Alliance for Peace and Democracy (Hong Kong)\",\n    \"US 2004 Presidential Election\",\n    \"Mukteswara Temple\",\n    \"42nd International Emmy Awards\",\n    \"Algiers Expedition (1519)\",\n    \"Dragon Quest: Monster Battle Road Victory\",\n    \"Jock Ewart\",\n    \"Edward Unton\",\n    \"That Second-Rate Warrior Is Now an Overpowered Mage!\",\n    \"Ukraine in World War II\",\n    \"2002 in the Republic of Ireland\",\n    \"Yankee–Pennamite Wars\",\n    \"Twenty-first century BC\",\n    \"Agriculture in lithuania\",\n    \"Fielden, Edward\",\n    \"Anwar Ali (poet)\",\n    \"Thomas Edwards (heresiographer)\",\n    \"Marcin Kasprzak Monument\",\n    \"Pakistani prisoners of war in India\",\n    \"RM of Battle River\",\n    \"4000 Warner Boulevard\",\n    \"Alan Schwartz\",\n    \"McMillan Hall, Newton Stewart\",\n    \"2020-21 Queen's Park F.C. season\",\n    \"Bourgeoisie democracy\",\n    \"Kałęczyn, Warmian-Masurian Voivodeship\",\n    \"Battle of Peñuelas\",\n    \"Caravonica, Queensland\",\n    \"List of South Carolina Civil War Confederate units\",\n    \"Juno Award for Rap Recording of the Year\",\n    \"List of newspapers in Dominican Republic\",\n    \"1852 United States presidential election in Missouri\",\n    \"Pawar (surname)\",\n    \"Patrice Pike and the Black Box Rebellion\",\n    \"Battle of Hudson's Bay\",\n    \"1998 in the Republic of Ireland\",\n    \"List of the lengths of American participation in wars\",\n    \"Fergus Lee-Warner\",\n    \"Time in the Dominican Republic\",\n    \"Awards and nominations received by Wu-Lu\",\n    \"Draft:Timeline of Wikipedia conflict with the United States government\"\n  ],\n  \"pagination\": {\n    \"current_page\": 10409,\n    \"per_page\": 50,\n    \"total_articles\": 631730,\n    \"total_pages\": 12635\n  }\n}"
    }
  ]
}