{
  "content": [
    {
      "type": "text",
      "text": "{\n  \"articles\": [\n    \"Knights of the New Crusade\",\n    \"Netstorm: Islands at War\",\n    \"Monument (Blutengel album)\",\n    \"James Broward Story\",\n    \"King Sejong of Joseon\",\n    \"Doris Stuart Kngwarreye\",\n    \"Invasion of Minorca (1781)\",\n    \"Emperor of Vijayanagara\",\n    \"Queen Katherine of Aragon\",\n    \"Communist Party of Nepal (Revolutionary Maoist)\",\n    \"Draft:Sebring Historical Society (Sebring, FL)\",\n    \"Star wars rise of skywalker\",\n    \"Battle of Krushevo (Bear Stone)\",\n    \"Jurahareswarar temple, Kanchipuram\",\n    \"Bulgarian Association of Software Companies\",\n    \"Dynasty Warriors (2004 video game)\",\n    \"Hounded (The Walking Dead)\",\n    \"Taishō democracy\",\n    \"Jaiswar, Kurmi\",\n    \"Crystal Lake (historical)\",\n    \"Primetime Emmy Award for Outstanding Scripted Variety Series\",\n    \"Azalea Middle School (Brookings, Oregon)\",\n    \"Reward-to-variability ratio\",\n    \"The Self-Sufficient-ish Bible: An Eco-living Guide for the 21st Century\",\n    \"Draft:King of Foxes (band)\",\n    \"Pennard (electoral ward)\",\n    \"LINE TV Awards\",\n    \"Agriculture in The Gambia\",\n    \"History of ancient lebanon\",\n    \"Ancient Dacian warfare\",\n    \"Queen Farah of Iran\",\n    \"New Media Award\",\n    \"Heavy snowfall of late 2010 in the United Kingdom\",\n    \"Zaman Anwar\",\n    \"1st Blockbuster Entertainment Awards\",\n    \"TCA Award for Outstanding New Program\",\n    \"The Staten Island Quarantine War (1858)\",\n    \"1874 United States House of Representatives election in Delaware\",\n    \"Brianna Stewart\",\n    \"List of awards and nominations received by Aaliyah\",\n    \"Niagara Heritage Trail\",\n    \"1986 Hong Kong Film Awards\",\n    \"List of ancient drinks\",\n    \"Ancient accounts of Homer\",\n    \"The Lion, the Witch and the Wardrobe (film)\",\n    \"The Ward, Toronto\",\n    \"AIMS/ASICS Athlete of the Year Award\",\n    \"Battlefront II\",\n    \"Robert stewart, 1st earl of orkney\",\n    \"Taxation in United Kingdom\"\n  ],\n  \"pagination\": {\n    \"current_page\": 10519,\n    \"per_page\": 50,\n    \"total_articles\": 631730,\n    \"total_pages\": 12635\n  }\n}"
    }
  ]
}