{
  "content": [
    {
      "type": "text",
      "text": "{\n  \"articles\": [\n    \"Battle of Mount Badon\",\n    \"Shadow Warriors (disambiguation)\",\n    \"Finances of the Japanese Empire in China\",\n    \"15th Star Awards\",\n    \"Sons Of Sardaar: The Battle of Saragarhi\",\n    \"President Lee (disambiguation)\",\n    \"Bringing home the body of King Karl XII\",\n    \"List of Acts of the Parliament of the United Kingdom, 1815-1818\",\n    \"1918-1919 United Kingdom police strikes\",\n    \"JP Software TCMD32\",\n    \"Irish Film & Television Academy Awards\",\n    \"Joshua Edwards (boxer)\",\n    \"Sumathi Best Television Presenter Award\",\n    \"Bounds-checking elimination\",\n    \"Shukugawara Station (disambiguation)\",\n    \"The Republic of China Navy\",\n    \"Civil war in Bangladesh\",\n    \"1896 US presidential election in Alabama\",\n    \"SALT I treaty\",\n    \"Edward Hallet Carr\",\n    \"Warrensville Heights Schools\",\n    \"Trials and Judicial Hearings following the 2011 Egyptian Revolution\",\n    \"Ralph de Warenne, 1st Lord of Whitchurch\",\n    \"Historic Queen Creek, Arizona\",\n    \"Ward Hill\",\n    \"14th Screen Actors Guild Awards\",\n    \"1999 Queensland 500\",\n    \"United 93 Monument\",\n    \"Organisational-Personnel Commission of the Lao People's Revolutionary Party\",\n    \"Timeline of the 2007-08 Australian region cyclone season\",\n    \"King Vaclav (Wenceslas) IV of Bohemia\",\n    \"Heritage Farmstead Museum\",\n    \"Faceless Queen\",\n    \"Coat of arms of the Holy Roman Empire\",\n    \"List of Laureates of the Governor General's Award in Visual and Media Arts\",\n    \"2022 Gaza War\",\n    \"Potwar\",\n    \"List of presidents of the House of Councillors (Japan)\",\n    \"Warsaw (album)\",\n    \"Casualties of war in israel\",\n    \"Post-democracy\",\n    \"Miroslav Zei Award\",\n    \"Awards and nominations received by Amitabh Bachchan\",\n    \"Golden Globe Award\",\n    \"Queensland Government Architect\",\n    \"Rawwadid dynasty\",\n    \"War saint\",\n    \"Dynamic software updating\",\n    \"Department of Environment and Heritage\",\n    \"Government of the german democratic republic\"\n  ],\n  \"pagination\": {\n    \"current_page\": 10639,\n    \"per_page\": 50,\n    \"total_articles\": 631730,\n    \"total_pages\": 12635\n  }\n}"
    }
  ]
}