{
  "content": [
    {
      "type": "text",
      "text": "{\n  \"articles\": [\n    \"West Warwick (CDP), Rhode Island\",\n    \"THE Unesco Collection Of Traditional Music Of The World\",\n    \"Democratic Party presidential primaries, 1924\",\n    \"Deewar (TV series)\",\n    \"Republic of Macedonia national water polo team\",\n    \"King of Thebes\",\n    \"Warisnagar Assembly constituency\",\n    \"Battle of Aisne\",\n    \"Anchor Hocking\",\n    \"Australia And New Zealand Banking Group Limited\",\n    \"Gala Hollywood Farewell Salute to President Clinton\",\n    \"Schwarzwalder Fuchs\",\n    \"Martin Edward Malia\",\n    \"Medieval morocco\",\n    \"Ed King (American football)\",\n    \"May-Stringer Heritage Museum\",\n    \"Discovery Expedition (clothing)\",\n    \"Italy at the European Race Walking Team Championships\",\n    \"KS Polonia SPEC Warszawa\",\n    \"Warm Spring Creek\",\n    \"Melanesian culture\",\n    \"Waray literature\",\n    \"2024 Independence Bowl\",\n    \"Kwasi Kwarteng mini-budget crisis\",\n    \"Kingdom of Croatia (1527–1868)\",\n    \"President of the Congress of Deputies\",\n    \"Draft:Harvest (Secret Invasion)\",\n    \"Hinduism in Czech Republic\",\n    \"Battle of Pavan Khind\",\n    \"The Divine Right of Kings (poem)\",\n    \"Nantie Hayward\",\n    \"Battle of Winkowo\",\n    \"Wardang Island\",\n    \"Queen's Necklace\",\n    \"When You're Through Thinking, Say Yes\",\n    \"United States presidential election in Nevada, 1948\",\n    \"Checking Accounts\",\n    \"MechWarrior 1\",\n    \"American Civil War bibliography\",\n    \"Union Councils of Peshawar\",\n    \"Billboard Music Award for Top R&B Song\",\n    \"Song dynasty pass coins\",\n    \"Atyap kingdom\",\n    \"List of Acts of the Parliament of the United Kingdom, 1835-1839\",\n    \"Arthur Howard (disambiguation)\",\n    \"Postal system of the United Kingdom\",\n    \"Edward Roberts (New Zealand cricketer)\",\n    \"United States Senate Agriculture Subcommittee on Conservation, Forestry, and Natural Resources\",\n    \"Draft:Renaissance High School (Idaho)\",\n    \"Emperor Huai of Han\"\n  ],\n  \"pagination\": {\n    \"current_page\": 10840,\n    \"per_page\": 50,\n    \"total_articles\": 631730,\n    \"total_pages\": 12635\n  }\n}"
    }
  ]
}