{
  "content": [
    {
      "type": "text",
      "text": "{\n  \"articles\": [\n    \"Minnesota Vikings/Season by season\",\n    \"Opština Mešeišta, Republic of Macedonia\",\n    \"Battle of Baguashan\",\n    \"Background of the 2008 South Ossetia war\",\n    \"List of fictional astronauts (futuristic exploration of Moon)\",\n    \"Lists of open-source artificial intelligence software\",\n    \"List of Ancient Structures\",\n    \"Abdulaziz, King of Saudi Arabia\",\n    \"Rodger Ward\",\n    \"Funerary monument\",\n    \"The Emperor's Revenge\",\n    \"Battle of Bregalnica\",\n    \"5th United Kingdom general election\",\n    \"2019 Indian general election timeline\",\n    \"Council Working Party\",\n    \"Duel Masters: Nettō! Battle Arena\",\n    \"Newtown Hardware House\",\n    \"Alexandra Kingston\",\n    \"United Kingdom - Italy relations\",\n    \"Revolutionary Party of Guatemala\",\n    \"Rene And Georgette Magritte With Their Dog After the War\",\n    \"Billboard Music Award for Digital Song of the Year\",\n    \"List of wars: 1880–1889\",\n    \"Nileswaram\",\n    \"Soviet space exploration history on Soviet stamps\",\n    \"Italy's colonial campaigns\",\n    \"Science in the 21st century\",\n    \"Poppler (software)\",\n    \"The Republic of Macedonia\",\n    \"Forward Operating Base Gardez\",\n    \"Motor Transport Corps (United States Army) (World War One)\",\n    \"Zuwara Berber\",\n    \"President of the Presidium of the National Parliament of Croatia\",\n    \"Mong Kok Culture\",\n    \"Ai, Emperor\",\n    \"Highbury (Islington ward)\",\n    \"War of the Golden Stool\",\n    \"Elf-War\",\n    \"Peterston-super-Ely (electoral ward)\",\n    \"Republic of haiti\",\n    \"History of smoking in Turkey\",\n    \"The Return of the King\",\n    \"Draft:Colonial modernization theory in Korea\",\n    \"Smoking/No Smoking\",\n    \"IEEE Reynold B. Johnson Information Storage Systems Award\",\n    \"King-Casper-Ward-Bazemore House\",\n    \"World Fantasy Award-Life Achievement\",\n    \"Thin dwarf gecko\",\n    \"Persian-speaking people in Australia\",\n    \"King Sebastian of Portugal\"\n  ],\n  \"pagination\": {\n    \"current_page\": 10980,\n    \"per_page\": 50,\n    \"total_articles\": 631730,\n    \"total_pages\": 12635\n  }\n}"
    }
  ]
}