{
  "content": [
    {
      "type": "text",
      "text": "{\n  \"articles\": [\n    \"List of United Kingdom by-elections (1857–68)\",\n    \"North East Kingdom\",\n    \"Edward T. Fairchild (Wisconsin associate justice)\",\n    \"The Traitor: A Story of the Fall of the Invisible Empire\",\n    \"German occupation of Estonia during World War II\",\n    \"Queensland Academy of Sport Soccer Program\",\n    \"Coward-punch\",\n    \"Andrew J. Ward\",\n    \"Virginia State Route 669 (King William County)\",\n    \"Servants in Heaven, Kings in Hell\",\n    \"Kapileswarapuram\",\n    \"Mustoe, King George County, Virginia\",\n    \"Krzyż Powstania Warszawskiego\",\n    \"A Memory Called Empire\",\n    \"Western Togoland Rebellion\",\n    \"Somaliland Civil War\",\n    \"Angola (Portuguese Empire)\",\n    \"28th Critics' Choice Awards\",\n    \"Draft:The Reality War\",\n    \"Maharashtra State Film Award for Best Publicity Design\",\n    \"Saluzzo Race Walking School\",\n    \"List of awards and honours received by Angela Merkel\",\n    \"List of awards and nominations received by Choi Soo-young\",\n    \"Star Wars role-playing game (Wizards of the Coast)\",\n    \"Talking Lifestyle Melbourne\",\n    \"Battle of Empingham\",\n    \"Edward Owen (priest)\",\n    \"President-elect of Malawi\",\n    \"Warren D. Leary\",\n    \"Donald Wilbur Stewart\",\n    \"Emperor Shōwa of Japan\",\n    \"Treaty of Ganghwa\",\n    \"Petroleum Administration for War\",\n    \"Carl (The Walking Dead)\",\n    \"Attalid kingdom\",\n    \"Wamba, Democratic Republic of the Congo\",\n    \"Netwars\",\n    \"Palmito Ranch Battlefield\",\n    \"OrCAD (CAD software)\",\n    \"Second Congress of Polish Culture\",\n    \"Culture of Chelyabinsk Oblast\",\n    \"Human trafficking in Bulgaria\",\n    \"Tadashii Itsuwari Kara no Kishō\",\n    \"John Mackey Award\",\n    \"Život Award for TV Act of the Year\",\n    \"Collaborative information seeking\",\n    \"Revolution (Blackpool)\",\n    \"List of open-source configuration management software\",\n    \"Vice President of the Democratic People's Republic of Korea\",\n    \"Queen Elizabeth's Foundation for Disabled People\"\n  ],\n  \"pagination\": {\n    \"current_page\": 11481,\n    \"per_page\": 50,\n    \"total_articles\": 631730,\n    \"total_pages\": 12635\n  }\n}"
    }
  ]
}