{
  "content": [
    {
      "type": "text",
      "text": "{\n  \"articles\": [\n    \"Edward Anderson (20th-century Texas politician)\",\n    \"Information-revolution.org\",\n    \"Mr. King\",\n    \"Conquest of Samaria\",\n    \"Battleforge\",\n    \"James, Meadows & Howard\",\n    \"Wesley Warren Jr.\",\n    \"Draft:2028 United States presidential election in Nevada\",\n    \"Warwick Beauregards\",\n    \"Gravity (software)\",\n    \"List of international cricket centuries by Mahela Jayawardene\",\n    \"Battle of colberger heide\",\n    \"Karnataka State Film Award for Best Regional film\",\n    \"App Tracking Transparency\",\n    \"Virginia State Route 733 (Rockingham County)\",\n    \"Mundowran, Queensland\",\n    \"Edward Joseph Michaels\",\n    \"Memoirs from the Twentieth Century\",\n    \"Japanese invasion of Kota Bahru\",\n    \"2017 APRA Silver Scroll Awards\",\n    \"Were Were Liking\",\n    \"65th Fighter Wing (World War II)\",\n    \"BSWW Beach Soccer Rankings\",\n    \"Thomas Warren (disambiguation)\",\n    \"James Kingston\",\n    \"Star Wars: Episode 5 - The Empire Strikes Back\",\n    \"Freeware Advanced Audio Decoder\",\n    \"Recognition of the Traditional Owners of the Land\",\n    \"Walking Dead (comics)\",\n    \"United States Senate Foreign Relations Subcommittee on International Operations and Organizations, Democracy and Human Rights\",\n    \"The War Within (Shadows Fall album)\",\n    \"Tradition, Family, Property\",\n    \"Verena Winiwarter\",\n    \"2 Minute Warning\",\n    \"Citico (Tellico archaeological site)\",\n    \"Edward M. Pakenham\",\n    \"Timeline of Angers\",\n    \"40th Directors Guild of America Awards\",\n    \"The Persian Expedition (disambiguation)\",\n    \"List of people of the Three Kingdoms\",\n    \"Florida Patriot War\",\n    \"Battle of Wissembourg (disambiguation)\",\n    \"Draft:Azerbaijan Center for Democracy and Development\",\n    \"1940 US presidential election in New Hampshire\",\n    \"Talking dog\",\n    \"King's Pawn Game\",\n    \"Queen for Two Days\",\n    \"Republic of Macedonia-Greece relations\",\n    \"International Free and Open Source Software Law Review\",\n    \"Four Sons of King Henry V\"\n  ],\n  \"pagination\": {\n    \"current_page\": 12320,\n    \"per_page\": 50,\n    \"total_articles\": 631730,\n    \"total_pages\": 12635\n  }\n}"
    }
  ]
}