{
  "content": [
    {
      "type": "text",
      "text": "{\n  \"articles\": [\n    \"YouTube Awards\",\n    \"2004 US presidential election in the District of Columbia\",\n    \"Draft:Nika Award for Best Animated Film\",\n    \"French-speaking Parliament of Brussels\",\n    \"United Kingdom Atomic Energy Authority\",\n    \"Oedipus the King Oedipus Rex\",\n    \"Windward Islands xeric scrub\",\n    \"Aage Jørgensen (historian)\",\n    \"List of state leaders in the 19th century BC\",\n    \"United States Presidential election, 1968\",\n    \"Third World War (comics)\",\n    \"Dǎngxiàng coinage in the His Hsia Dynasty\",\n    \"Republic of loose\",\n    \"Caroline, Queen Consort\",\n    \"Military history of the Crusader states\",\n    \"Battle of Trevilian Station order of battle: Confederate\",\n    \"The Queen's Curse\",\n    \"List of ponds in the Czech Republic\",\n    \"Grimaldi dynasty\",\n    \"Blue Line (Newark Light Rail)\",\n    \"1816 US presidential election in Tennessee\",\n    \"Delaware Blue Hens\",\n    \"California during american civil war\",\n    \"King Gizzard & the Lizard Wizard\",\n    \"Minister of Agriculture and Food (Ontario)\",\n    \"History of ancient Israel and Judah (1000-63 BCE)\",\n    \"Warsaw Accord\",\n    \"South Koreans in the Republic of China\",\n    \"Exploration of Polydeuces\",\n    \"Congo (Democratic Republic of)\",\n    \"R/SandersForPresident\",\n    \"Dwile flonking\",\n    \"Treasure chest (historical)\",\n    \"National bank of the kyrgyz republic\",\n    \"Bangladesh Liberation War Stadium\",\n    \"2013 Africa Magic Viewers' Choice Awards\",\n    \"United States presidential election, 1816\",\n    \"Queen Charlotte merchant ship\",\n    \"Working Group on Planetary System Nomenclature\",\n    \"King of the herrings\",\n    \"Salt Creek (Muskingum County, Ohio)\",\n    \"Francis Edward McLean\",\n    \"Age of Sail Heritage Museum\",\n    \"The Independence Angel\",\n    \"List of monuments in Taganrog\",\n    \"Barakula, Queensland\",\n    \"19th century in United States history\",\n    \"The Republican (Springfield)\",\n    \"Jainacharya Yugbhushan Surishwarji\",\n    \"Tony Stark: Iron Man: War of the Realms\"\n  ],\n  \"pagination\": {\n    \"current_page\": 2298,\n    \"per_page\": 50,\n    \"total_articles\": 631730,\n    \"total_pages\": 12635\n  }\n}"
    }
  ]
}