{
  "content": [
    {
      "type": "text",
      "text": "{\n  \"articles\": [\n    \"King of the Grizzlies\",\n    \"Shared-source software\",\n    \"Veretzky (Rabbinical dynasty)\",\n    \"Minister of Foreign Affairs (Democratic Republic of the Congo)\",\n    \"Monumento histórico\",\n    \"Breast cancer culture\",\n    \"Acts and Monuments\",\n    \"Chai (king of Ayutthaya)\",\n    \"Venezuelan presidential election, 1947\",\n    \"Dissolution of the Union of Socialist Soviet Republics\",\n    \"Battle of the Standard\",\n    \"The Battle of Monte Cassino\",\n    \"Emperor Wenmu\",\n    \"Sunset and the Mockingbird\",\n    \"Ward, Nicholas\",\n    \"Waterloo Warriors men's basketball\",\n    \"List of Premiers of the People's Republic of China\",\n    \"German speaking community in Belgium\",\n    \"12th TCA Awards\",\n    \"TheSmokingGun.com\",\n    \"Football in the Republic of Ireland\",\n    \"Kuru kingdom (Mahabharata)\",\n    \"Email blasting software\",\n    \"List of kings of Jordan\",\n    \"U.K.-Czech Republic relations\",\n    \"The Warmasters\",\n    \"Expansion of Amsterdam since the 19th century\",\n    \"Delaware Bike Route 1\",\n    \"Walking Far From Home\",\n    \"Night of the Day of the Dawn of the Son ... Part 2: In Shocking 2-D\",\n    \"Jerard Fund Award\",\n    \"Mountain Flycatcher-warbler\",\n    \"1973 Mazamas Aconcagua expedition\",\n    \"Draft:Conrad Warren\",\n    \"All Elite Wrestling Revolution\",\n    \"Dwarven language (disambiguation)\",\n    \"Gholam Serwar Nasher\",\n    \"Society of Film and Television Arts Television Awards 1961\",\n    \"Edward Aylmer Digby\",\n    \"Queen Consort Caroline\",\n    \"Edward Rollins (disambiguation)\",\n    \"Sakhr Software Company\",\n    \"Edward Rubenstein\",\n    \"International Heritage Inc.\",\n    \"Wallingford, Queensland\",\n    \"UMlalazi dwarf chameleon\",\n    \"The History Channel: Great Battles of Rome\",\n    \"Sharon Keillor Award for Women in Engineering Education\",\n    \"Emperor Constantine IX Monomachos\",\n    \"Italian support for Iraq during the Iran–Iraq war\"\n  ],\n  \"pagination\": {\n    \"current_page\": 2923,\n    \"per_page\": 50,\n    \"total_articles\": 631730,\n    \"total_pages\": 12635\n  }\n}"
    }
  ]
}