{
  "content": [
    {
      "type": "text",
      "text": "{\n  \"articles\": [\n    \"The Battle of Jutland\",\n    \"List of diplomats from the United Kingdom to Hanover\",\n    \"James Hayward (artist)\",\n    \"List of Battles of World War I\",\n    \"Independence Stadium (disambiguation)\",\n    \"Kingdom of the Hellenes\",\n    \"Penn State-Delaware County Nittany Lions\",\n    \"1946 Alabama Commissioner of Agriculture election\",\n    \"List of Shinhwa's awards\",\n    \"Sino-Burmese Wars (1765-1769)\",\n    \"Gallic wars\",\n    \"Shanxi Coking (Group)\",\n    \"The Story of Civilization\",\n    \"Draft:Chris Lamb (software developer)\",\n    \"Battle of the Bloody Angle\",\n    \"George Carwardine\",\n    \"Timeline of Sanaʽa\",\n    \"Rational Software development\",\n    \"2022 Vice Presidential election of India\",\n    \"°W (Warnerke)\",\n    \"The Clayton-Bulwer Treaty\",\n    \"U.S. Commission on National Security/21st Century\",\n    \"Hugh Cleghorn (colonial administrator)\",\n    \"White Sulphur Springs order of battle\",\n    \"Delaware State Wildlife Areas\",\n    \"Human trafficking in Virginia\",\n    \"5th Annual Logie Awards\",\n    \"Nikkan Sports Film Award for Best Supporting Actor\",\n    \"Knight Empire\",\n    \"A King's Tale\",\n    \"List of awards and nominations received by Bryan Cranston\",\n    \"Military history of the Mi’kmaq Warriors\",\n    \"United States presidential election in Georgia, 1964\",\n    \"PEN/Jean Stein Book Award\",\n    \"Southwark Christchurch\",\n    \"20 century\",\n    \"King Ranch (Tully River Station)\",\n    \"EU Commissioner for Agriculture and Food\",\n    \"William Edward Cule\",\n    \"Battles of the Soissonnais\",\n    \"Colonial Uganda\",\n    \"Keith Top of the Pops and His Minor UK Indie Celebrity All-Star Backing Band\",\n    \"Battle of sandfontein\",\n    \"ITA Software\",\n    \"Midland Warriors\",\n    \"CineMAA Award for Best Story\",\n    \"Wąwozowa Street, Warsaw\",\n    \"Ghulam Sarwar Sr.\",\n    \"Breaking News in Yuba County\",\n    \"Amoy (linguistics)/Negative particles/traditional\"\n  ],\n  \"pagination\": {\n    \"current_page\": 3101,\n    \"per_page\": 50,\n    \"total_articles\": 631730,\n    \"total_pages\": 12635\n  }\n}"
    }
  ]
}