{
  "content": [
    {
      "type": "text",
      "text": "{\n  \"articles\": [\n    \"Omani Civil War\",\n    \"Bhoomi (Software)\",\n    \"James Edward Sewell\",\n    \"Arnold Schwartzennegger\",\n    \"King Solomon Academy\",\n    \"Draft:Venkateshwara Temple, Allipur\",\n    \"San Francisco Film Critics Circle Award for Best Animated Feature\",\n    \"Warnig\",\n    \"SS Empire Gawain\",\n    \"Software licence key\",\n    \"Shaw – Howard University (Washington Metro)\",\n    \"List of Ethiopian-Somali wars en conflicts\",\n    \"Timeline of Hangzhou\",\n    \"Revolutions in Mathematics\",\n    \"Kree–Skrull War (Marvel Cinematic Universe)\",\n    \"Siddeshwar Swami\",\n    \"2005 Honduran presidential election\",\n    \"Edward Fitzgerald (brewer)\",\n    \"William Hayward\",\n    \"Edward Charles Close junior\",\n    \"Battle of Rakowitz\",\n    \"Privileged bodies of the United Kingdom\",\n    \"Order of battle at the Battle of Monmouth\",\n    \"Edward Reed (naval architect)\",\n    \"Miskito Kingdom\",\n    \"Advances in Agriculture\",\n    \"List of Golden Globe Awards: Supporting Actor\",\n    \"Wessell \\\"Warmdaddy\\\" Anderson\",\n    \"T. Edward Reed\",\n    \"Rama Rao Pawar\",\n    \"List of Ukrainian flag officers losses during the Russo-Ukrainian War\",\n    \"Sam Woodward\",\n    \"1990 Origins Award winners\",\n    \"Declaration of Independence (painting)\",\n    \"List of Discovery +254 episodes\",\n    \"Gajapati Empire\",\n    \"List of Hindu temples in the United Kingdom\",\n    \"Independence (Minnesota)\",\n    \"Orders, decorations and medals of the United Kingdom\",\n    \"Battle of the Caudine Forks (321 BC)\",\n    \"Avionics software\",\n    \"United States presidential election, 1876\",\n    \"Perry Wilbon Howard I\",\n    \"1968 Icelandic presidential election\",\n    \"Kingma system\",\n    \"Warradarge\",\n    \"Carolopolis Award\",\n    \"Christopher Wardale\",\n    \"Dance Dance Revolution Extreme Limited Edition Music Sampler\",\n    \"Chapter 22 (Star Wars: Clone Wars)\"\n  ],\n  \"pagination\": {\n    \"current_page\": 3823,\n    \"per_page\": 50,\n    \"total_articles\": 631730,\n    \"total_pages\": 12635\n  }\n}"
    }
  ]
}