{
  "content": [
    {
      "type": "text",
      "text": "{\n  \"articles\": [\n    \"Soldiers, a history of men in battle\",\n    \"Battle of xincheng\",\n    \"Dunfermline Queen Margaret\",\n    \"1876 United States presidential election in Louisiana\",\n    \"East Timorese independence referendum, 1999\",\n    \"Grammy Awards 2016\",\n    \"The Wayward Girl (1957 film)\",\n    \"People's Republic of Serbia\",\n    \"Luminex Software, Inc.\",\n    \"Meta-historical fall\",\n    \"Asturian Revolution\",\n    \"Birmingham and Warwick Junction Canal Navigation Act 1840\",\n    \"First Peoples' Heritage, Language and Culture Council\",\n    \"Phillip Schwartzerd\",\n    \"Lockheed EC-121H-LO Warning Star\",\n    \"Shadow president\",\n    \"Culture of Western Australia\",\n    \"Empire State Pride Agenda Foundation\",\n    \"Assembled: The Making of Ms. Marvel\",\n    \"Ruqaiyyah Waris Maqsood\",\n    \"Warren Moise\",\n    \"Sinsinwar\",\n    \"Battle music (video game music)\",\n    \"Striking Out\",\n    \"Phra Nakhon Khiri historical park\",\n    \"Interstate 295 (Delaware–Pennsylvania)\",\n    \"Exploration of 2P/Encke\",\n    \"Discovery Airways\",\n    \"Toward a Constitution\",\n    \"Working f-number\",\n    \"Emperor Taitsung of Tang\",\n    \"Battle of Egypt\",\n    \"Genie Music Awards\",\n    \"Cartoon Wars Part I\",\n    \"Rameswaram-Manduadih Express\",\n    \"Dacian Empire\",\n    \"Ward No. 8 (Dhaka South City Corporation)\",\n    \"United States presidential election in South Dakota, 1948\",\n    \"Discoveryland\",\n    \"Journal of Discourses By President John Taylor, His Counselors and Others\",\n    \"The Swarm (1966 film)\",\n    \"Division of illawarra\",\n    \"East Side High School (Newark, New Jersey)\",\n    \"Stewardship areas of New Zealand\",\n    \"List of baronetcies in the Baronetage of the United Kingdom: F\",\n    \"Nietjaervi Battle\",\n    \"List of awards and nominations received by Just Shoot Me!\",\n    \"Brother Warth\",\n    \"Anglo french war of 1778 1783\",\n    \"Agency banking model\"\n  ],\n  \"pagination\": {\n    \"current_page\": 4194,\n    \"per_page\": 50,\n    \"total_articles\": 631730,\n    \"total_pages\": 12635\n  }\n}"
    }
  ]
}