{
  "content": [
    {
      "type": "text",
      "text": "{\n  \"articles\": [\n    \"Hostage-taking in a penal colony in Volgograd\",\n    \"Animal Cell Culture\",\n    \"List of British brigades of the Second World War\",\n    \"National Football League Comeback Player of the Year award\",\n    \"List of Hawaii Warriors bowl games\",\n    \"Edward Alexander Welters\",\n    \"Finch (software)\",\n    \"Cultural heritage sites in Pyeongchang County\",\n    \"List of wars in Asia\",\n    \"Ancient pamphylia\",\n    \"Schwarzenberg (Switzerland)\",\n    \"Strategic Air Command in the United Kingdom\",\n    \"Spanish Civil War chronology 1936\",\n    \"Software architects\",\n    \"Party for the Basque Revolution\",\n    \"Energy and facility management software\",\n    \"TripRewards.com\",\n    \"Warsaw Theatre Directorate\",\n    \"2nd Battle Squadron (United Kingdom)\",\n    \"Battle of Kara Killisse (1918)\",\n    \"Starrcade '91: Battlebowl – The Lethal Lottery\",\n    \"Vietnam War Song Project (VWSP)\",\n    \"HMAS Warramunga\",\n    \"1966 Syrian revolution\",\n    \"Han Xian (Han dynasty)\",\n    \"Republic of Texas - U.S. relations\",\n    \"Dawar Kundi\",\n    \"Warsaw, Georgia\",\n    \"Union of South Africa King's Medal for Bravery, Silver\",\n    \"Staffordshire Yeomanry (Queen's Own Royal Regiment)\",\n    \"Ajj akhaan Waris Shah nu\",\n    \"4 civilizations\",\n    \"Great War for the Empire\",\n    \"Loaisa Expedition\",\n    \"Dag Heward-Mills\",\n    \"2013 Windward Islands Tournament\",\n    \"Content discovery\",\n    \"Independence Theory in Combinatorics\",\n    \"Czech republic/Economy\",\n    \"Arts & Culture Trust Awards\",\n    \"Asa, Kwara State\",\n    \"Malaya at the 1950 British Empire Games\",\n    \"University Of Arid Agriculture\",\n    \"Stewardship Incentives Program\",\n    \"List of municipal presidents of Monterrey\",\n    \"British Academy Children's Award for Animation\",\n    \"BRIT Awards 2009\",\n    \"Bruce Edward Holder, Sr\",\n    \"Draft:Edward Harwood\",\n    \"List of battles and operations in the 1948 Arab-Israeli War\"\n  ],\n  \"pagination\": {\n    \"current_page\": 4290,\n    \"per_page\": 50,\n    \"total_articles\": 631730,\n    \"total_pages\": 12635\n  }\n}"
    }
  ]
}