{
  "content": [
    {
      "type": "text",
      "text": "{\n  \"articles\": [\n    \"Edward Longueville\",\n    \"Doctor who monster invasion trading card game\",\n    \"Shaanxi province (Yuan dynasty)\",\n    \"Battle of Faesulae (225 BC)\",\n    \"List of Roman Emperors\",\n    \"Edward Kean\",\n    \"Legia Warsaw (basketball)\",\n    \"Traditional Mexican music\",\n    \"Wartime Prohibition Act\",\n    \"List of Presidents of Suriname\",\n    \"Ottoman-Habsburg wars\",\n    \"Arthur \\\"Waring\\\" Bowen\",\n    \"List of Northern Exposure awards and nominations\",\n    \"Edward Wilfred Harry Travis\",\n    \"Terrorism Early Warning Wroups\",\n    \"Warriar\",\n    \"Heritage cinema\",\n    \"The Treaty of Ripon\",\n    \"List of Joe Biden 2020 presidential campaign municipal endorsements\",\n    \"Henrique da Costa Mecking\",\n    \"Republic of Korea women's national football team\",\n    \"List of awards and nominations received by Arrested Development\",\n    \"Duckwalking\",\n    \"Cracking of hydrocarbons\",\n    \"War Remembrance Cross\",\n    \"Primetime Emmy Award for Outstanding Variety, Music, or Comedy Special\",\n    \"Felix Schwarzenberg\",\n    \"1852 US presidential election in New York\",\n    \"Queen Of Brush County\",\n    \"Eleazer Kingsbury Foster Jr.\",\n    \"Opinion polling for the 1950 United Kingdom general election\",\n    \"Look to Windward\",\n    \"Virginia State Route 629 (King William County)\",\n    \"Moldavian–Polish War (disambiguation)\",\n    \"Mockingjay Part 2\",\n    \"Battle of the Sea of Azov\",\n    \"Treaty of Casalanza\",\n    \"Viennese Emperor Moth\",\n    \"Armed Forces of the Republic of the Congo\",\n    \"BBC People's War\",\n    \"Anthony Dwayne Ware\",\n    \"Sarah Cahill (beauty queen)\",\n    \"Howard Payne University at New Braunfels\",\n    \"List of awards and nominations received by Patrick Stewart\",\n    \"Ward 2 (Chicago)\",\n    \"George Warwick\",\n    \"Procedural democracy\",\n    \"Janikow-Folwark\",\n    \"Battle of Bolia\",\n    \"John Edwards (poet)\"\n  ],\n  \"pagination\": {\n    \"current_page\": 5273,\n    \"per_page\": 50,\n    \"total_articles\": 631730,\n    \"total_pages\": 12635\n  }\n}"
    }
  ]
}