{
  "content": [
    {
      "type": "text",
      "text": "{\n  \"articles\": [\n    \"Mac Giolla Phádraig dynasty\",\n    \"Battle of Avignon\",\n    \"Dwarf nealie\",\n    \"1924 United States presidential election in Nebraska\",\n    \"1st Marine Raider Battalion (Second World War)\",\n    \"INA War Museum\",\n    \"Wartensteinbahn\",\n    \"The king is dead long live the king\",\n    \"Embassy of the Islamic Republic of Mauritania in Ottawa\",\n    \"Endorsements in the 1920 Republican Party presidential primaries\",\n    \"Lærdal farmers' rebellion\",\n    \"Warhammer Online: Wrath of Heroes\",\n    \"Sánchez, Dominican Republic\",\n    \"List of Star Wars planets\",\n    \"Serbia, republic of\",\n    \"Warwick Council election, 2011\",\n    \"World War Z 2\",\n    \"Pencil Award\",\n    \"Mary Kingsbury Simkhovitch\",\n    \"Choudwar (Odisha Vidhan Sabha constituency)\",\n    \"Draft:Batman and Superman: Battle of the Super Sons\",\n    \"Lauhitya kingdom\",\n    \"List of preserved Warrington buses\",\n    \"Glenn T. Seaborg (awards and honors)\",\n    \"Edward Owen Hefford\",\n    \"Arwarton, Suffolk\",\n    \"Andrew II, King of Hungary\",\n    \"Impeachment trial of President Trump\",\n    \"Sushun, Emperor\",\n    \"Indian states rankings\",\n    \"Information-centric networking\",\n    \"Texas Band of Traditional Kickapoo\",\n    \"Jimi \\\"The Human\\\" Hocking\",\n    \"List of states in the Holy Roman Empire/M\",\n    \"Abyssal Warriors\",\n    \"Battle of Guaxenduba\",\n    \"Backward message\",\n    \"A. W. Ward\",\n    \"The President's Keeper\",\n    \"The 2nd Great War\",\n    \"Culture of Belarus\",\n    \"7th British Academy Video Games Awards\",\n    \"Discovery Channel (Indian TV channel)\",\n    \"Dwars door de Westhoek\",\n    \"US presidential elections in Delaware\",\n    \"Battle of Maarrat al-Nu'man\",\n    \"Rey Bulwark\",\n    \"Edward Fahey\",\n    \"2001 ENnie Award winners\",\n    \"2021 in the Czech Republic\"\n  ],\n  \"pagination\": {\n    \"current_page\": 5365,\n    \"per_page\": 50,\n    \"total_articles\": 631730,\n    \"total_pages\": 12635\n  }\n}"
    }
  ]
}