{
  "content": [
    {
      "type": "text",
      "text": "{\n  \"articles\": [\n    \"Treaty of Altranstadt (1707)\",\n    \"Grand Queen Dowager Seongryeol\",\n    \"Dluzyna, Warmian-Masurian Voivodeship\",\n    \"Culture of Philadelphia\",\n    \"Stewards' Challenge Cup\",\n    \"Bar Kochba Rebellion\",\n    \"Latin American revolutions\",\n    \"President of tynwald\",\n    \"Monitor (Vietnam War)\",\n    \"10th Ward Chicago\",\n    \"Pucikwar\",\n    \"Reginald F. Lewis Museum of Maryland African American History & Culture\",\n    \"Forced labour of Poles after World War II\",\n    \"Carlow Historical & Archaeological Society\",\n    \"Ancient Egyptian race controversy\",\n    \"Kree–Nova War\",\n    \"Treaty of Pozwoł\",\n    \"The Republic of North Macedonia\",\n    \"Christ the King Catholic School\",\n    \"New Zealand Department of Agriculture\",\n    \"1889 Central Cumberland colonial by-election (disambiguation)\",\n    \"Elliot Norton Awards\",\n    \"10th ARIA Music Awards\",\n    \"Edward M. Hundert\",\n    \"Freddie Warren (footballer born 1992)\",\n    \"Nagash (Warhammer)\",\n    \"Moscow–Peking\",\n    \"Department of Tourism, Culture, Industry and Innovation (Newfoundland and Labrador)\",\n    \"Edward Feetham Coates\",\n    \"Republic of Ukraine\",\n    \"Kingsmill, Robert\",\n    \"Thirumakaraleeswarar Temple\",\n    \"The War of the Amazon\",\n    \"Battle of Pusan (1597)\",\n    \"Kharyyalakh, Verkhnevilyuysky District, Sakha Republic\",\n    \"House of Cards Awards\",\n    \"Academy Award for Best Short Film - Live Action - 2 Reels\",\n    \"American Ninja Warrior (season 10)\",\n    \"Rocking Moon\",\n    \"Davey O'Brien National Quaterback Award\",\n    \"Alonso Edwards\",\n    \"Making Monsters (song)\",\n    \"List of diplomatic missions of the Donetsk People's Republic\",\n    \"Windows Vista networking features\",\n    \"Sean King (water polo)\",\n    \"Sorcerer King\",\n    \"Litmus (Battlestar Galactica 2003)\",\n    \"World War II military history\",\n    \"Heyward, Keith\",\n    \"Republic of Senegal\"\n  ],\n  \"pagination\": {\n    \"current_page\": 5477,\n    \"per_page\": 50,\n    \"total_articles\": 631730,\n    \"total_pages\": 12635\n  }\n}"
    }
  ]
}