{
  "content": [
    {
      "type": "text",
      "text": "{\n  \"articles\": [\n    \"NFL Play of the Year Award\",\n    \"Kurdish Independence Movement in Turkey\",\n    \"Reg Ward\",\n    \"Culture of Corruption\",\n    \"Bollywood Movie Award - Best Costume Designer\",\n    \"Anglo-Spanish War (1585-1604)\",\n    \"Murray Merle Schwartz\",\n    \"Battle of Bornhöved (798)\",\n    \"List of acts of the Parliament of the United Kingdom from 1912\",\n    \"National RTI Awards\",\n    \"Fortunatus William Lilley Dwarris\",\n    \"Obesity in the United Kingdom\",\n    \"List of Consolidated Fund Acts from the 20th century\",\n    \"List of all naval vessels current and former of the United Kingdom\",\n    \"Battle of Antrea\",\n    \"Rebellion (manga volume)\",\n    \"List of Guggenheim Fellowships awarded in 1984\",\n    \"Kingston-upon-Thames by-election, 1972\",\n    \"Talking Tom Cat 2\",\n    \"Austrian post offices in the Ottoman Empire\",\n    \"Edward LeRoy Rice\",\n    \"Limeking\",\n    \"11th President of the US\",\n    \"Kostolac-Kocofeni culture\",\n    \"Zodiac Mindwarp My Life Story\",\n    \"Dates of establishment of diplomatic relations with the Qing dynasty\",\n    \"George M. Warren\",\n    \"Mary, queen consort of James II and VII\",\n    \"Kingdom of Niebla\",\n    \"Warragul Burrowing Crayfish\",\n    \"Gadani Ship Breaking Yard\",\n    \"Pink revolution\",\n    \"US presidential election, 1960\",\n    \"Interwar\",\n    \"Kazanka, Blagoveshchensky District, Republic of Bashkortostan\",\n    \"Queen Heonui\",\n    \"Critics' Choice Super Award for Best Actor in a Horror Series, Limited Series or Made-for-TV Movie\",\n    \"Order of the Republic (Sierra Leone)\",\n    \"Canadian Screen Award for Best Actor\",\n    \"Edward Faitoute Condict Young\",\n    \"2007 Prince Edward Island election\",\n    \"Empire of Dirt (film)\",\n    \"Taking Dawn\",\n    \"CreamWare Audio GmbH\",\n    \"Armour Packing Plant\",\n    \"Frederick A.O. Schwarz Sr.\",\n    \"Krasnaya Zvezda, Republic of Bashkortostan\",\n    \"The UN Security Council and war on Iraq\",\n    \"Bengal Film Journalists' Association – Best Cinematographer Award\",\n    \"Horizon Discovery\"\n  ],\n  \"pagination\": {\n    \"current_page\": 5635,\n    \"per_page\": 50,\n    \"total_articles\": 631730,\n    \"total_pages\": 12635\n  }\n}"
    }
  ]
}