{
  "content": [
    {
      "type": "text",
      "text": "{\n  \"articles\": [\n    \"Battle of the Theben Pass\",\n    \"President of the Departmental Council of Corrèze\",\n    \"Geurrila warfare\",\n    \"Justin King (entrepreneur)\",\n    \"Content-aware scale\",\n    \"Battle of Waterloo (disambiguation)\",\n    \"French battleship Hoche (1886)\",\n    \"Leamington and Warwick Tramways Order 1879\",\n    \"Asian/Pacific American Award for Literature\",\n    \"Glide (software)\",\n    \"2014 Windward Islands Tournament squads\",\n    \"Dean and Provost of Southwark\",\n    \"Nobel award in economics\",\n    \"Milton Mallawarachchi discography\",\n    \"2015 New England Revolution season\",\n    \"Infoware\",\n    \"Stewart D. McInnes\",\n    \"Sarah Warren Keeler\",\n    \"List of awards won by Apple Daily\",\n    \"Chozhas dynasty\",\n    \"Rebel Assault 2: The Hidden Empire\",\n    \"Główczyn-Towarzystwo\",\n    \"List of awards and nominations received by Zayn Malik\",\n    \"Goddess-queen\",\n    \"Kingston, AL\",\n    \"HRE Emperor\",\n    \"Atlantic treaty association\",\n    \"Mecklenburg declaration of independence\",\n    \"Union for Struggle for the Emancipation of the Working class\",\n    \"Cole and Edwards\",\n    \"United States presidential election in New Mexico, 2008\",\n    \"First Warning (weather)\",\n    \"Ancient greek dialects\",\n    \"Flat Earth News: An Award-winning Reporter Exposes Falsehood, Distortion and Propaganda in the Global Media\",\n    \"Book of the Kings of Judah and Israel\",\n    \"Baz's Culture Clash\",\n    \"Ancient Age (whiskey)\",\n    \"Second Battle of Narvik\",\n    \"The Accident (Dynasty)\",\n    \"1888 Central Cumberland colonial by-election (disambiguation)\",\n    \"Battle of Talataye (2022)\",\n    \"Noel Edward Hilliam\",\n    \"Museum of the King's Regiment\",\n    \"Historical research\",\n    \"Isitwalandwe Award\",\n    \"InterContinental Warsaw\",\n    \"2014 McMurry War Hawks football team\",\n    \"List of vapourware\",\n    \"People's Republic of China - Romania relations\",\n    \"Hvar culture\"\n  ],\n  \"pagination\": {\n    \"current_page\": 5739,\n    \"per_page\": 50,\n    \"total_articles\": 631730,\n    \"total_pages\": 12635\n  }\n}"
    }
  ]
}