{
  "content": [
    {
      "type": "text",
      "text": "{\n  \"articles\": [\n    \"Nima Abu-Wardeh\",\n    \"George W. Stocking Jr.\",\n    \"Jon Edwards (chess player)\",\n    \"Warszawa Ochota railway station\",\n    \"Battle of Fulhope Law\",\n    \"King Henry VIII School, Abergavenny\",\n    \"Minister of Justice of the Republic of Latvia\",\n    \"Bapawar\",\n    \"Battle of the bulge\",\n    \"Costa Rican jade tradition\",\n    \"List of awards received by Leonard Bernstein\",\n    \"Traditional religions in Papua New Guinea\",\n    \"The United Kingdom of Great Britain and Ireland\",\n    \"Wrestle Kingdom 12 in Tokyo Dome\",\n    \"Caution Never Won a War\",\n    \"Commission on oil independence\",\n    \"Majmac al-tawarikh\",\n    \"Website tracking\",\n    \"King Hamad of Bahrain\",\n    \"Thomas Howard (British Army officer)\",\n    \"Commandant of the Republic of Korea Marine Corps\",\n    \"Kilwa, Democratic Republic of the Congo\",\n    \"Declaration of Independence of the Democratic Republic of Viet Nam\",\n    \"Twenty-sixth Vice President of the United States\",\n    \"Leonidas Warren Payne Jr.\",\n    \"Comparison of optimization software\",\n    \"Culture of Kiel\",\n    \"Taiwan Revolutionary Party\",\n    \"Lesnica, Warmian-Masurian Voivodeship\",\n    \"Karl Philipp Fuerst zu Schwarzenberg\",\n    \"Antismoking campaign\",\n    \"Dano-Swedish War (1657-1658)\",\n    \"The battle for middle earth 2\",\n    \"Renaissance of the 11th century\",\n    \"Monipuri monuments in Bangladesh\",\n    \"International Film Music Critics Association Award for Best Original Score for a Drama Film\",\n    \"Helen Edwards (artist)\",\n    \"Martens's Warbler\",\n    \"Zaguri Empire\",\n    \"Queen of Great Britain and Northern Ireland\",\n    \"Battle of Le Cresson\",\n    \"Edward Nevill, 15th Baron Bergavenny\",\n    \"Ward (song)\",\n    \"Port of London (Extension of Seaward Limit) Act 1964\",\n    \"Alliance for democracy and federation\",\n    \"List of ancient spiral stairs\",\n    \"To Bed to Battle\",\n    \"Halych–Volhynia Wars\",\n    \"Quicksilver software\",\n    \"Greek Baths in ancient Olympia\"\n  ],\n  \"pagination\": {\n    \"current_page\": 5802,\n    \"per_page\": 50,\n    \"total_articles\": 631730,\n    \"total_pages\": 12635\n  }\n}"
    }
  ]
}