{
  "content": [
    {
      "type": "text",
      "text": "{\n  \"articles\": [\n    \"Kings Bay Base, Georgia\",\n    \"Nursery (horticulture)\",\n    \"RTNDA Edward R. Murrow Award\",\n    \"Titan Wars (video game)\",\n    \"Od Warszawy do Ojcowa. Przygody w podróży po kraju\",\n    \"1999 Sri Lankan presidential election\",\n    \"The Last Warrior 3\",\n    \"Second barons war\",\n    \"Edward Hawkins (New York politician)\",\n    \"Emperor dragonfly\",\n    \"Emperor Xiaowu of Northern Wei\",\n    \"County Route 42 (Warren County, New York)\",\n    \"Red Dwarf series VII\",\n    \"List of international presidential trips made by Moon Jae-in\",\n    \"Vicariate of Queensland\",\n    \"The Day of Revolution\",\n    \"Brazilian Music Award\",\n    \"Edward French (make-up artist)\",\n    \"Connor Edwards\",\n    \"United Kingdom general election, 2005\",\n    \"Steel (Battle Beast album)\",\n    \"Preparatory work of a treaty\",\n    \"Charlie Chan and the Curse of the Dragon Queen\",\n    \"Edward McNiven\",\n    \"Uncle Bob Maza Award\",\n    \"Battle of Veii (396 BC)\",\n    \"Secretary for Agriculture, Fisheries and Conservation\",\n    \"List of acts of the Parliament of the United Kingdom, 1820–1824\",\n    \"Ancient greek comedy\",\n    \"United States House Agriculture Subcommittee on Conservation, Research, and Biotechnology\",\n    \"Orrin Woodward\",\n    \"Queen of Hearts (Once Upon a Time)\",\n    \"Warthead blenny\",\n    \"Emperor Alexander (1813 ship)\",\n    \"Alexandra, queen consort of Edward VII of Great Britain\",\n    \"Treaty of Dover\",\n    \"Viking ring castles\",\n    \"National Democracy (Belgium)\",\n    \"Battle of Salt Creek\",\n    \"Zen Kajiwara\",\n    \"Far Eastern Civilization\",\n    \"The Best of the Star Wars Adventure Journal\",\n    \"Prince Edward Island Route 336\",\n    \"Central African Republic-China relations\",\n    \"The Battlefield series\",\n    \"Congo (the Democratic Republic of the)\",\n    \"Azerbaijani wedding traditions\",\n    \"Middle Kingdom of the Hittites\",\n    \"Dominican Republic-Haiti border\",\n    \"White-throated kingbird\"\n  ],\n  \"pagination\": {\n    \"current_page\": 6176,\n    \"per_page\": 50,\n    \"total_articles\": 631730,\n    \"total_pages\": 12635\n  }\n}"
    }
  ]
}