{
  "content": [
    {
      "type": "text",
      "text": "{\n  \"articles\": [\n    \"North Hamgyeong Province (Republic of Korea)\",\n    \"Edward Holmes (field hockey)\",\n    \"Dead Man Walking (2 Chainz and Future song)\",\n    \"Mutual Defense Treaty (United States-South Korea)\",\n    \"War on the Saints\",\n    \"Holding On (The War on Drugs song)\",\n    \"National Museum of the Democratic Republic of the Congo\",\n    \"Battle of Haditha Dam\",\n    \"War of the Worldviews\",\n    \"9th Politburo of the Lao People's Revolutionary Party\",\n    \"Timeline of computing 1980–89\",\n    \"Union order of battle at the Second Battle of Corinth\",\n    \"Battle of Shadadeh\",\n    \"Battle of tettenhall\",\n    \"Edward Kennion\",\n    \"Taurida Soviet Socialist Republic\",\n    \"Edwards vs Aguillard\",\n    \"1998 President of the Hong Kong Legislative Council election\",\n    \"Scottish Football League Yearly Awards\",\n    \"1948: A History of the First Arab-Israeli War\",\n    \"733d Aircraft Control and Warning Squadron\",\n    \"Gwendolyn S. King\",\n    \"Warsaw Theatre\",\n    \"Saga of King Hrolf Kraki\",\n    \"1978 Battle at Lisnamuck\",\n    \"NUTS statistical regions of the United Kingdom\",\n    \"1960 United States presidential election in Missouri\",\n    \"Postal counties in the United Kingdom\",\n    \"Steve Wariner discography\",\n    \"Islamic Revolutionary Guard Corps Air-Force\",\n    \"30th European Film Awards\",\n    \"Highland Council wards and councillors 1999 to 2003\",\n    \"2023 Israeli-Hamas war\",\n    \"John Murphy (Queen of the South footballer)\",\n    \"MV Empire Favourite\",\n    \"List of Vice Presidents of Liberia\",\n    \"Traditional Phenological Knowledge\",\n    \"US invasion of Japan\",\n    \"Optical motion tracking\",\n    \"Virginia State Route 705 (Rockingham County)\",\n    \"Warner Home\",\n    \"International Labor and Working-Class History\",\n    \"Kingsport Police Department (Tennessee)\",\n    \"Timeline of the Northern Mali conflict\",\n    \"Reactions to the end of the Sri Lankan Civil War\",\n    \"Gmina Gowarczów\",\n    \"Mobile ransomware\",\n    \"1976 Queen's Birthday Honours\",\n    \"Sea Sponge Aquaculture\",\n    \"List of Rajyotsava award recipients (1966-1970)\"\n  ],\n  \"pagination\": {\n    \"current_page\": 650,\n    \"per_page\": 50,\n    \"total_articles\": 631730,\n    \"total_pages\": 12635\n  }\n}"
    }
  ]
}