{
  "content": [
    {
      "type": "text",
      "text": "{\n  \"articles\": [\n    \"21st (Service) Battalion, King's Royal Rifle Corps (Yeoman Rifles)\",\n    \"Combined New South Wales–Queensland Country\",\n    \"Battle of Gate Pā\",\n    \"Charles Edward Cotton\",\n    \"United States aircraft production during World War II\",\n    \"Shadow-masking\",\n    \"European Main Battle Tank (EMBT)\",\n    \"Turkish Basketball President Cup\",\n    \"Nutmeg Book Award\",\n    \"Amyand Buckingham\",\n    \"That Awkward Moment\",\n    \"Sarah Edwards (missionary)\",\n    \"Tottori City Historical Museum\",\n    \"Dalit warfare\",\n    \"1946-1947 Montenegrin Republic League\",\n    \"Ministry of the Interior of the Republic of China\",\n    \"Louisiana–Monroe Warhawks men's basketball\",\n    \"Ward missionaries\",\n    \"Draft:33 Revolutions per Minute (book)\",\n    \"Bagienice-Folwark\",\n    \"Charles Edward Davis\",\n    \"Goya Award for Best Editing\",\n    \"Warsaw-Śródmieście\",\n    \"Lepidus's Rebellion\",\n    \"William Donlon Edwards\",\n    \"Cherry picking tax avoidance\",\n    \"1886 Queen's County Ossory by-election\",\n    \"President Nguyễn\",\n    \"Athletics at the 1938 British Empire Games - Women's high jump\",\n    \"Licchavi Republic\",\n    \"Russian Ministry of Culture\",\n    \"MASCARET (Software)\",\n    \"Independence Day Star Wars\",\n    \"Ancient persian units of measurement\",\n    \"Mesumundu Archaeological Park\",\n    \"Golden Globe Award for Best Performance by an Actor in a Mini-Series or Motion Picture Made for Television\",\n    \"Kareem Abdul-Jabbar Social Justice Champion Award\",\n    \"Chicago Film Critics Association Awards 2005\",\n    \"Battle of Jordanów\",\n    \"Everybody Thinks We're Drag Queens\",\n    \"Maurice Wilkes Award\",\n    \"Andy Warhol (David Bowie song)\",\n    \"United States presidential election in Georgia, 2012\",\n    \"Abaga, Olyokminsky District, Sakha Republic\",\n    \"Bhubaneswar-Junagarh Express\",\n    \"Saawariya\",\n    \"2011-12 Golden State Warriors season\",\n    \"List of premiers of Queensland by time in office\",\n    \"Homefront in First World War\",\n    \"KBS Music Awards\"\n  ],\n  \"pagination\": {\n    \"current_page\": 7179,\n    \"per_page\": 50,\n    \"total_articles\": 631730,\n    \"total_pages\": 12635\n  }\n}"
    }
  ]
}