{
  "content": [
    {
      "type": "text",
      "text": "{\n  \"articles\": [\n    \"Electronic Battle Weapon 4\",\n    \"History of the United Kingdom during WWI\",\n    \"List of Presidents of the National Assembly of Angola\",\n    \"HM King Henry VIII\",\n    \"Draft:18th Asian Film Awards\",\n    \"Kingston Frontenacs (EPHL)\",\n    \"Edward J. Roye\",\n    \"Francisco Hernández Expedition (1570-77)\",\n    \"Artifact Dota\",\n    \"2nd Washington D.C. Area Film Critics Association Awards\",\n    \"Battle of the Goehrde\",\n    \"Iranian invasion of Indus Valley\",\n    \"War of the Javanese-Malay\",\n    \"List of U.S. colonial possessions\",\n    \"28th Air Expeditionary Wing\",\n    \"Rungwa (Tanzanian ward)\",\n    \"Central Philippine University - College of Agriculture, Resources and Environmental Sciences\",\n    \"Science and Culture Today\",\n    \"2013 New Zealand Warriors season\",\n    \"Frank L. Howard\",\n    \"The War of the Sixth Coalition\",\n    \"1927 Latvian presidential election\",\n    \"BAFTA Cymru Awards\",\n    \"List of cruisers of the Republic of China Navy\",\n    \"The October Revolution (album)\",\n    \"Toi invasion\",\n    \"List of 2019 box office number-one films in the United Kingdom\",\n    \"Buckingham Palace\",\n    \"Howard Edward Butt Sr.\",\n    \"John Ericsson Monument\",\n    \"Maningrida Arts & Culture\",\n    \"Howard Hilstrom\",\n    \"Sydney Swans Grand Finals in the 21st century\",\n    \"Alive & Kicking (Nana Mizuki album)\",\n    \"King Henry VIII's College\",\n    \"National Archaeological Museum of Korçë\",\n    \"Prince Edward Abnel Keliihonui Piikoi\",\n    \"Sis (Armenian Kingdom of Cilicia)\",\n    \"Timeline of the Palestine region\",\n    \"King Longshanks\",\n    \"4th National Television Awards\",\n    \"History of Jordan-United Kingdom relations\",\n    \"Battle of Phaleron\",\n    \"Pakistan independence\",\n    \"Micronesian culture\",\n    \"FRET (Software)\",\n    \"Learning on Screen Awards\",\n    \"Larry King (King of Kensington)\",\n    \"Cooking with recipes\",\n    \"Podali Shankar Rajeshwar\"\n  ],\n  \"pagination\": {\n    \"current_page\": 8684,\n    \"per_page\": 50,\n    \"total_articles\": 631730,\n    \"total_pages\": 12635\n  }\n}"
    }
  ]
}