{
  "content": [
    {
      "type": "text",
      "text": "{\n  \"articles\": [\n    \"Conversations (software)\",\n    \"Treaty of Alcovas (1479)\",\n    \"The King of Fighters 2002\",\n    \"Independent Spirit Awards 1998\",\n    \"Sugar House Monument\",\n    \"The Fighting Coward (film)\",\n    \"Edward Wynne (disambiguation)\",\n    \"My War (disambiguation)\",\n    \"Edward Henry A'Court\",\n    \"2014–15 NLEX Road Warriors season\",\n    \"Schwartz-Matsuo syndrome\",\n    \"In the King of Prussia\",\n    \"Computer software compatibility\",\n    \"Awards and nominations received by Will Smith\",\n    \"Beyblade Burst Dynamite Battle\",\n    \"Presidium of the Supreme Soviet of the Azerbaijan Soviet Socialist Republic\",\n    \"Hayward Shepherd\",\n    \"PVL Finals Most Valuable Player award\",\n    \"Great Battle\",\n    \"Pandya dynasty\",\n    \"Dr. Who: Daleks Invasion Earth 2150 A.D.\",\n    \"Ancient American civilisations\",\n    \"Shaw–Howard University station\",\n    \"Goods Island, Queensland\",\n    \"Kopyovo, Kopyovsky Settlement Council, Ordzhonikidzevsky District, Republic of Khakassia\",\n    \"1997-98 Golden State Warriors season\",\n    \"Swarajyarakshak Sambhaji (2017 TV Series)\",\n    \"List of awards and nominations received by Dulce María\",\n    \"Critics' Circle National Dance Awards\",\n    \"Graham Wardle\",\n    \"Battle of Leyte\",\n    \"Bill King (Australian rugby league)\",\n    \"John Howard Lundrigan\",\n    \"Breaking bad franchise\",\n    \"Queen of the Nile (disambiguation)\",\n    \"Time-aware LSTM\",\n    \"The King's Demons\",\n    \"N.B.Ward\",\n    \"Karen (The Walking Dead)\",\n    \"MuchMusic Video Award for Peoples Choice: Favourite International Video\",\n    \"Fourteenth Dynasty of Hùng kings\",\n    \"Faster (Star Wars: The Bad Batch)\",\n    \"Barking Town Urban District Tramways Order 1899\",\n    \"Maude Trotter Steward\",\n    \"Presidents of Cricket Association of Bengal\",\n    \"Tolon, Lensky District, Sakha Republic\",\n    \"Edward Hanlan\",\n    \"New rock revolution\",\n    \"Leftwing Revolutionary Nationalist Movement - 20th Century\",\n    \"List of Indian presidents by date of birth\"\n  ],\n  \"pagination\": {\n    \"current_page\": 8697,\n    \"per_page\": 50,\n    \"total_articles\": 631730,\n    \"total_pages\": 12635\n  }\n}"
    }
  ]
}