{
  "content": [
    {
      "type": "text",
      "text": "{\n  \"articles\": [\n    \"Nemesis of the Roman Empire\",\n    \"Timeline of Pavia\",\n    \"Vans Agnew Monument\",\n    \"Culture of Liberia\",\n    \"Hardwar (video game)\",\n    \"Treaty of Hudaibia\",\n    \"1872 US presidential election in West Virginia\",\n    \"Elbert A. Woodward\",\n    \"Draft:Untitled Warhammer 40,000 television series\",\n    \"Proclamation of the Kingdom of Italy\",\n    \"Tatsuno Kingo\",\n    \"Democratic party 2020 presidential primaries\",\n    \"A. Anwar Rhazza\",\n    \"2005-06 Golden State Warriors\",\n    \"Battle of the Elleporus\",\n    \"Cesar award\",\n    \"List of Nabataean Kings\",\n    \"Democratic Revolutionary Peoples Party\",\n    \"Vice-president of the United States\",\n    \"Mornington Peninsula Regional Gallery Works on Paper Award\",\n    \"John Middleton (colonial administrator)\",\n    \"58th Academy Awards nominees\",\n    \"Oshima-Sawara Station\",\n    \"List of hospitals in the Czech Republic\",\n    \"Al-Musawar\",\n    \"Czechoslovak Republic (1918–1938)\",\n    \"List of adaptations of works by Stephen King\",\n    \"Warranty services\",\n    \"List of colonial heads of Italian Somaliland\",\n    \"Books about the Korean War\",\n    \"8th Pride of Britain Awards\",\n    \"Edward Greitzer\",\n    \"Charlie Stewart (Australian rules footballer born 1939)\",\n    \"Frank Howard Building\",\n    \"Edward B. Pond\",\n    \"Tony Sale Award\",\n    \"Age of Empires II HD: The Rise of the Rajas\",\n    \"Ocinebrina edwardsi cincta\",\n    \"Louisiana-Monroe Warhawks football seasons\",\n    \"Open Culture\",\n    \"Israel-Gaza war (2023-present)\",\n    \"Warriors of the Deep\",\n    \"Pro Wrestling Illustrated awards\",\n    \"Bloom (software)\",\n    \"English invasion of Scotland (1385)\",\n    \"King Phumiphon\",\n    \"Donateware\",\n    \"Draft:National Board of Review Award for Best Directorial Debut\",\n    \"Warbles\",\n    \"King Abdullah Bin Abdulaziz Airport\"\n  ],\n  \"pagination\": {\n    \"current_page\": 9165,\n    \"per_page\": 50,\n    \"total_articles\": 631730,\n    \"total_pages\": 12635\n  }\n}"
    }
  ]
}